cvgl_data-0.1.3.dist-info/LICENSE
cvgl_data-0.1.3.dist-info/RECORD
cvgl_data-0.1.3.dist-info/top_level.txt
cvgl_data-0.1.3.dist-info/WHEEL
cvgl_data-0.1.3.dist-info/METADATA
cvgl_data.libs/libgssapi_krb5-497db0c6.so.2.2
cvgl_data.libs/libquadmath-96973f99.so.0.0.0
cvgl_data.libs/libsqlite3-f79e2a86.so.0.8.6
cvgl_data.libs/libselinux-0922c95c.so.1
cvgl_data.libs/libpcre-9513aab5.so.1.2.0
cvgl_data.libs/libkeyutils-dfe70bd6.so.1.5
cvgl_data.libs/libproj-24128ac9.so.25.9.3.0
cvgl_data.libs/libcom_err-2abe824b.so.2.1
cvgl_data.libs/libk5crypto-b1f99d5c.so.3.1
cvgl_data.libs/liblapack-1ad85175.so.3.4.2
cvgl_data.libs/libkrb5-fcafa220.so.3.3
cvgl_data.libs/libkrb5support-d0bcff84.so.0.1
cvgl_data.libs/libssl-cd1d6220.so.1.0.2k
cvgl_data.libs/libcrypto-d3570994.so.1.0.2k
cvgl_data.libs/libjbig-78348776.so.2.0
cvgl_data.libs/libjpeg-43436dd5.so.62.1.0
cvgl_data.libs/libtiff-b6eb22fb.so.5.2.0
cvgl_data.libs/libgfortran-91cc3cb1.so.3.0.0
cvgl_data.libs/libblas-357956a1.so.3.4.2
cvgl_data/visualize.py
cvgl_data/backend.cpython-39-x86_64-linux-gnu.so
cvgl_data/util.py
cvgl_data/__init__.py
cvgl_data/prepare.py
cvgl_data/paired.py
